sktopt/__init__.py
sktopt/core/__init__.py
sktopt/core/derivatives.py
sktopt/core/misc.py
sktopt/core/optimizers/__init__.py
sktopt/core/optimizers/common.py
sktopt/core/optimizers/linearlagrangian.py
sktopt/core/optimizers/loglagrangian.py
sktopt/core/optimizers/logmoc.py
sktopt/core/optimizers/oc.py
sktopt/core/projection.py
sktopt/core/visualization.py
sktopt/fea/__init__.py
sktopt/fea/composer.py
sktopt/fea/solver.py
sktopt/filter/__init__.py
sktopt/filter/helmholtz.py
sktopt/mesh/__init__.py
sktopt/mesh/loader.py
sktopt/mesh/task.py
sktopt/mesh/toy_problem.py
sktopt/mesh/utils.py
sktopt/mesh/visualization.py
sktopt/tools/__init__.py
sktopt/tools/history.py
sktopt/tools/logconf.py
sktopt/tools/scheduler.py
sktopt-0.1.7.dist-info/LICENSE
sktopt-0.1.7.dist-info/METADATA
sktopt-0.1.7.dist-info/WHEEL
sktopt-0.1.7.dist-info/RECORD
